quasi_utils/oms.py
quasi_utils/utils.py
quasi_utils-1.3.12.dist-info/LICENSE
quasi_utils-1.3.12.dist-info/METADATA
quasi_utils-1.3.12.dist-info/WHEEL
quasi_utils-1.3.12.dist-info/top_level.txt
quasi_utils-1.3.12.dist-info/RECORD
