Metadata-Version: 2.1
Name: quasi-utils
Version: 1.3.12
Summary: Utilities for OMS
Author-email: Kaustubh Dixit <hi.stockemy@gmail.com>
License: Copyright (c) 2022 The Python Packaging Authority
Keywords: trading,algorithm,nifty
Classifier: License :: OSI Approved :: MIT License
Classifier: Programming Language :: Python
Classifier: Programming Language :: Python :: 3
Requires-Python: >=3.10
License-File: LICENSE
Requires-Dist: requests
